datathief/__init__.py
datathief/datathief.py
datathief/version.py
datathief-0.3.dist-info/LICENSE
datathief-0.3.dist-info/METADATA
datathief-0.3.dist-info/WHEEL
datathief-0.3.dist-info/top_level.txt
datathief-0.3.dist-info/RECORD
