Metadata-Version: 2.1
Name: datathief
Version: 0.3
Summary: Simple utility for extracting data from images
Home-page: https://github.com/sciris/datathief
Author: Cliff Kerr
Author-email: info@sciris.org
License: UNKNOWN
Keywords: data,imageextraction,thievery
Platform: OS Independent
Classifier: Environment :: Console
Classifier: Intended Audience :: Science/Research
Classifier: License :: Other/Proprietary License
Classifier: Operating System :: OS Independent
Classifier: Programming Language :: Python
Classifier: Topic :: Software Development :: Libraries :: Python Modules
Classifier: Development Status :: 5 - Production/Stable
Classifier: Programming Language :: Python :: 3.8
Requires-Dist: numpy
Requires-Dist: matplotlib
Requires-Dist: sciris
